pidev/Joystick.py
pidev/LidarSensor.py
pidev/MixPanel.py
pidev/RPiMIB.py
pidev/STEPPER.md
pidev/SlaveMaster.py
pidev/TemperatureSensor.py
pidev/__init__.py
pidev/slush_manager.py
pidev/speaker.py
pidev/stepper.py
pidev/stepperutilities.py
pidev/Cyprus_Commands/Cyprus_Commands_RPi.py
pidev/Cyprus_Commands/__init__.py
pidev/Cyprus_Commands/readme.md
pidev/ShutdownModule/README.md
pidev/ShutdownModule/install-power-shutdown.sh
pidev/ShutdownModule/power_shutdown/Makefile
pidev/ShutdownModule/power_shutdown/power_shutdown.c
pidev/kivy/AdminScreen.kv
pidev/kivy/AdminScreen.py
pidev/kivy/DPEAButton.kv
pidev/kivy/DPEAButton.py
pidev/kivy/ImageButton.py
pidev/kivy/PassCodeScreen.kv
pidev/kivy/PassCodeScreen.py
pidev/kivy/PauseScreen.kv
pidev/kivy/PauseScreen.py
pidev/kivy/SelfUpdatingLabel.md
pidev/kivy/__init__.py
pidev/kivy/selfupdatinglabel.py
pidev/kivy/images/DPEALogoTransparent.png
pidev/kivy/images/shadow.png
pidev/kivy/images/white.png
pidev-1.0.dist-info/METADATA
pidev-1.0.dist-info/WHEEL
pidev-1.0.dist-info/licenses/LICENSE.txt
pidev-1.0.dist-info/RECORD
